beancode/__init__.py
beancode/bean_ast.py
beancode/bean_ffi.py
beancode/cfgparser.py
beancode/cli/beancode.py
beancode/cli/beanfmt.py
beancode/error.py
beancode/formatter.py
beancode/interpreter.py
beancode/lexer.py
beancode/libroutines.py
beancode/modules/__init__.py
beancode/modules/beanray.py
beancode/modules/beanstd.py
beancode/optimizer.py
beancode/parser.py
beancode/repl.py
beancode/runner.py
beancode/tracer.py
beancode-0.7.0.dist-info/METADATA
beancode-0.7.0.dist-info/WHEEL
beancode-0.7.0.dist-info/entry_points.txt
beancode-0.7.0.dist-info/licenses/LICENSE.md
beancode-0.7.0.dist-info/RECORD
