Metadata-Version: 2.4
Name: beancode
Version: 0.7.0
Summary: A portable, dependency-free IGCSE/O-Level Computer Science (0478, 0984, 2210) Pseudocode interpreter.
License: MPL-2.0
License-File: LICENSE.md
Author: ezntek
Author-email: eason@ezntek.com
Requires-Python: >=3.10,<4.0
Classifier: License :: OSI Approved
Classifier: Programming Language :: Python :: 3
Classifier: Programming Language :: Python :: 3.10
Classifier: Programming Language :: Python :: 3.11
Classifier: Programming Language :: Python :: 3.12
Classifier: Programming Language :: Python :: 3.13
Classifier: Programming Language :: Python :: 3.14
